{
  "section": "8",
  "title": "Section 8 - Examen clinique - Épaule",
  "content": "8. Questionnaire subjectif et état actuel\nAppréciation subjective de l’évolution : Le travailleur rapporte ne pas être en mesure de reprendre son travail prélésionnel. Il n’a pas pensé à une réorientation de carrière et il ne sait pas ce qui pourrait faire d’autre que son travail d’installateur de comptoirs. Il est frustré par la situation.\nPlaintes et problèmes : Il se plaint principalement de douleurs et d’inflammation au niveau de son épaule gauche. Il décrit la douleur comme un élancement. Il rapporte une exacerbation de la douleur à l’épaule gauche avec les mouvements au-dessus de la tête. Il rapporte que les gestes de tirer des objets sont difficiles à réaliser et note une diminution de la force et de l’endurance musculaire au niveau de son membre supérieur gauche.\nAu niveau de son rachis cervical, il note une douleur qui descend jusqu’à son épaule gauche, au niveau du grand pectoral ainsi qu’à l’omoplate gauche. Il note une douleur irradiante qui descend jusqu’au bras et au niveau des doigts D4 et D5 gauche. Il rapporte occasionnellement des engourdissements aux deux bras lorsque qu’il est en position assise prolongée. Il note une diminution de la dextérité fine au niveau de sa main gauche.\nIl rapporte des éveils nocturnes secondaires à de la douleur à l’épaule gauche ainsi que des engourdissements au niveau de son membre supérieur gauche.\nIl nie toute raideur matinale et tout symptôme sphinctérien.\nImpact sur AVQ/AVD : cf feuille en annexe",
  "tags": [
    "examen_clinique",
    "épaule",
    "rachis",
    "membre_supérieur"
  ],
  "source_file": "204_MS2-2-5-conso.docx",
  "language": "fr",
  "category": "examen_clinique",
  "complexity": "medium"
}